django_auth_gitlab/oidc.py
django_auth_gitlab/urls.py
django_auth_gitlab/views.py
django_auth_gitlab-0.1.0.dist-info/DESCRIPTION.rst
django_auth_gitlab-0.1.0.dist-info/METADATA
django_auth_gitlab-0.1.0.dist-info/RECORD
django_auth_gitlab-0.1.0.dist-info/WHEEL
django_auth_gitlab-0.1.0.dist-info/metadata.json
django_auth_gitlab-0.1.0.dist-info/top_level.txt
django_auth_gitlab-0.1.0.dist-info/zip-safe
