Metadata-Version: 2.0
Name: django-auth-gitlab
Version: 0.1.0
Summary: OpenID Connect authentication support for Django
Home-page: https://github.com/LEW21/django-auth-gitlab
Author: Linus Lewandowski
Author-email: linus@lew21.net
License: LGPLv2+
Keywords: django,auth,oauth,openid,oidc,social,gitlab
Platform: UNKNOWN
Classifier: Development Status :: 4 - Beta
Classifier: Intended Audience :: System Administrators
Classifier: Natural Language :: English
Classifier: License :: OSI Approved :: GNU Lesser General Public License v2 or later (LGPLv2+)
Classifier: Programming Language :: Python
Classifier: Programming Language :: Python :: 3
Classifier: Programming Language :: Python :: 3.5
Classifier: Programming Language :: Python :: 3.6
Classifier: Topic :: System :: Systems Administration :: Authentication/Directory
Requires-Dist: django (>=1.10.0)
